cellhint/__init__.py
cellhint/align.py
cellhint/correspond.py
cellhint/distance.py
cellhint/distances.py
cellhint/harmonize.py
cellhint/integrate.py
cellhint/logger.py
cellhint/pct.py
cellhint/plot.py
cellhint/symbols.py
cellhint-1.0.0.dist-info/LICENSE
cellhint-1.0.0.dist-info/METADATA
cellhint-1.0.0.dist-info/WHEEL
cellhint-1.0.0.dist-info/top_level.txt
cellhint-1.0.0.dist-info/RECORD
